ygitchangelog/__init__.py
ygitchangelog/gitchangelog.rc.reference
ygitchangelog/gitchangelog.rc.reference.v2.1.3
ygitchangelog/ygitchangelog.py
ygitchangelog/templates/mako/ChangeLog.tpl
ygitchangelog/templates/mako/octobercms-plugin.tpl
ygitchangelog/templates/mako/restructuredtext.tpl
ygitchangelog/templates/mustache/markdown.tpl
ygitchangelog/templates/mustache/restructuredtext.tpl
ygitchangelog-1.0.2.dist-info/LICENSE
ygitchangelog-1.0.2.dist-info/METADATA
ygitchangelog-1.0.2.dist-info/WHEEL
ygitchangelog-1.0.2.dist-info/entry_points.txt
ygitchangelog-1.0.2.dist-info/top_level.txt
ygitchangelog-1.0.2.dist-info/RECORD
