Metadata-Version: 2.1
Name: ygitchangelog
Version: 1.0.2
Summary: UTF support for gitchangelog. (gitchangelog generates a changelog thanks to git log.)
Home-page: https://github.com/yedhrab/ygitchangelog
Author: Yunus Emre Ak
Author-email: yedhrab@gmail.com
License: MIT
Keywords: changelog,gitchangelog,ygitchangelog
Platform: UNKNOWN
Classifier: Development Status :: 3 - Alpha
Classifier: Intended Audience :: Developers
Classifier: Topic :: Software Development :: Build Tools
Classifier: License :: OSI Approved :: MIT License
Classifier: Programming Language :: Python :: 3
Classifier: Programming Language :: Python :: 3.4
Classifier: Programming Language :: Python :: 3.5
Classifier: Programming Language :: Python :: 3.6
Requires-Dist: pystache
